shelflet/__init__.py
shelflet/main.py
shelflet/tests/__init__.py
shelflet-0.1.5.dist-info/LICENSE
shelflet-0.1.5.dist-info/METADATA
shelflet-0.1.5.dist-info/WHEEL
shelflet-0.1.5.dist-info/top_level.txt
shelflet-0.1.5.dist-info/RECORD
