Metadata-Version: 2.1
Name: shelflet
Version: 0.1.5
Summary: The Python shelve module except with optional serializers and compression to make smaller shelves!
Home-page: https://github.com/mullenkamp/shelflet
Author: Mike Kittridge
Author-email: mullenkamp1@gmail.com
License: Apache
Keywords: shelve
Classifier: Development Status :: 3 - Alpha
Classifier: Intended Audience :: Developers
Classifier: License :: OSI Approved :: Apache Software License
Classifier: Programming Language :: Python :: 3.8
Classifier: Programming Language :: Python :: 3.9
License-File: LICENSE
